dsavinified/__init__.py
dsavinified/main.py
dsavinified-0.1.0.dist-info/LICENSE
dsavinified-0.1.0.dist-info/METADATA
dsavinified-0.1.0.dist-info/WHEEL
dsavinified-0.1.0.dist-info/top_level.txt
dsavinified-0.1.0.dist-info/RECORD
